{
    "os": "Linux-4.15.0-197-generic-x86_64-with-glibc2.27",
    "python": "3.10.8",
    "heartbeatAt": "2023-02-19T14:20:24.942130",
    "startedAt": "2023-02-19T14:20:24.269074",
    "docker": null,
    "cuda": null,
    "args": null,
    "state": "running",
    "program": "IC/knowledge-distillation_antigo.ipynb",
    "root": "/home/luigi-doria",
    "host": "ml",
    "username": "luigi-doria",
    "executable": "/home/luigi-doria/miniconda3/bin/python",
    "cpu_count": 4,
    "cpu_count_logical": 8,
    "cpu_freq": {
        "current": 1.524125,
        "min": 800.0,
        "max": 4500.0
    },
    "cpu_freq_per_core": [
        {
            "current": 1.251,
            "min": 800.0,
            "max": 4500.0
        },
        {
            "current": 0.83,
            "min": 800.0,
            "max": 4500.0
        },
        {
            "current": 1.705,
            "min": 800.0,
            "max": 4500.0
        },
        {
            "current": 2.647,
            "min": 800.0,
            "max": 4500.0
        },
        {
            "current": 1.999,
            "min": 800.0,
            "max": 4500.0
        },
        {
            "current": 1.227,
            "min": 800.0,
            "max": 4500.0
        },
        {
            "current": 1.431,
            "min": 800.0,
            "max": 4500.0
        },
        {
            "current": 1.103,
            "min": 800.0,
            "max": 4500.0
        }
    ],
    "disk": {
        "total": 915.3223114013672,
        "used": 345.84594345092773
    },
    "gpu": "NVIDIA GeForce GTX 1060 6GB",
    "gpu_count": 1,
    "gpu_devices": [
        {
            "name": "NVIDIA GeForce GTX 1060 6GB",
            "memory_total": 6371475456
        }
    ],
    "memory": {
        "total": 7.717708587646484
    }
}
